MANIFEST.in
README.rst
setup.py
bin/jira-bulk-loader.py
jira_bulk_loader.egg-info/PKG-INFO
jira_bulk_loader.egg-info/SOURCES.txt
jira_bulk_loader.egg-info/dependency_links.txt
jira_bulk_loader.egg-info/requires.txt
jira_bulk_loader.egg-info/top_level.txt
jirabulkloader/__init__.py
jirabulkloader/interface.py
jirabulkloader/task_extractor.py
jirabulkloader/task_extractor_exceptions.py