Metadata-Version: 1.1
Name: jira-bulk-loader
Version: 0.3.0
Summary: Create tasks in Jira via RESTful API
Home-page: https://github.com/oktopuz/jira-bulk-loader
Author: Alexander Dudko
Author-email: alex.dudko@gmail.com
License: Apache 2.0
Platform: UNKNOWN
Classifier: Development Status :: 4 - Beta
Classifier: Environment :: Console
Classifier: Intended Audience :: Information Technology
Classifier: Operating System :: OS Independent
Classifier: Programming Language :: Python :: 2.7
Classifier: Programming Language :: Python :: 3.4
Classifier: Topic :: Utilities
Classifier: License :: OSI Approved :: Apache Software License
